rsnapsim/AuxCodonDicts.py
rsnapsim/CodonDictionaries.py
rsnapsim/DiffusionRateCalc.py
rsnapsim/FileParser.py
rsnapsim/GenericMetaData.py
rsnapsim/GenericSSA.py
rsnapsim/IntensityAnalyses.py
rsnapsim/ModelBuilder.py
rsnapsim/ModelBuilder_bk.py
rsnapsim/ODE_Soln.py
rsnapsim/ProbeVectorFactory.py
rsnapsim/PropensityFactory.py
rsnapsim/RibosomeAnalyses.py
rsnapsim/SSA_Soln.py
rsnapsim/SequenceManipMethods.py
rsnapsim/SequenceManipMethods_bk.py
rsnapsim/TranslationOptimization.py
rsnapsim/TranslationSolvers.py
rsnapsim/__init__.py
rsnapsim/_version.py
rsnapsim/blank_model.cpp
rsnapsim/blank_model.h
rsnapsim/blank_model.pyx
rsnapsim/core.py
rsnapsim/custom_errors.py
rsnapsim/expv.py
rsnapsim/expvt.py
rsnapsim/generic_solvers.py
rsnapsim/poi.py
rsnapsim/rsnapsim_model_maker.py
rsnapsim/setup_blank.py
rsnapsim/tRNAmap.py
rsnapsim/translation_models.py
rsnapsim/data_files/gobert_2020_PA_values.txt
rsnapsim/gene_files/Bactin_withTags.txt
rsnapsim/gene_files/H2B_2tags.txt
rsnapsim/gene_files/H2B_withTags.txt
rsnapsim/gene_files/HUMINSR.gb
rsnapsim/gene_files/KDM5B.txt
rsnapsim/gene_files/KDM5B_withTags.txt
rsnapsim/gene_files/NC_005816.gb
rsnapsim/gene_files/Plasmid_H2B.txt
rsnapsim-0.0.58.dist-info/LICENCE.txt
rsnapsim-0.0.58.dist-info/METADATA
rsnapsim-0.0.58.dist-info/WHEEL
rsnapsim-0.0.58.dist-info/top_level.txt
rsnapsim-0.0.58.dist-info/RECORD
