Metadata-Version: 2.1
Name: rsnapsim
Version: 0.0.58
Summary: A package for mRNA sequence translation stochastic simulations
Home-page: UNKNOWN
Author: Dr. Luis Aguilera, William Raymond, Dr. Brian Munsky
Author-email: wsraymon@rams.colostate.edu
License: UNKNOWN
Platform: UNKNOWN
Classifier: Programming Language :: Python :: 3
Classifier: License :: OSI Approved :: MIT License
Classifier: Operating System :: OS Independent
License-File: LICENCE.txt
Requires-Dist: BioPython
Requires-Dist: numpy
Requires-Dist: scipy
Requires-Dist: cython
Requires-Dist: matplotlib
Requires-Dist: pandas
Requires-Dist: snapgene-reader
Requires-Dist: dna-features-viewer
